beebeesheep.py
beebeesheep-1.3.dist-info/METADATA
beebeesheep-1.3.dist-info/WHEEL
beebeesheep-1.3.dist-info/top_level.txt
beebeesheep-1.3.dist-info/RECORD
