Metadata-Version: 2.1
Name: beebeesheep
Version: 1.3
Summary: this module can print bee bee im sheep
Home-page: https://afdian.net/a/cleversheep
Author: cleversheep2011
Author-email: cleversheep2011@outlook.com
License: MIT
Platform: UNKNOWN
